stockpricealert/__init.__.py
stockpricealert/bot.py
stock_price_alert-1.0.2.dist-info/METADATA
stock_price_alert-1.0.2.dist-info/WHEEL
stock_price_alert-1.0.2.dist-info/top_level.txt
stock_price_alert-1.0.2.dist-info/RECORD
