Metadata-Version: 2.1
Name: stock-price-alert
Version: 1.0.2
Summary: A Python library for retrieving stock prices and setting price alerts
Home-page: https://github.com/piritheeviraman/stock-price-alert-lib
Author: piritheevi
Author-email: gkappdeveloper@gmail.com
Classifier: Development Status :: 3 - Alpha
Classifier: Intended Audience :: Developers
Classifier: License :: OSI Approved :: MIT License
Classifier: Programming Language :: Python
Classifier: Programming Language :: Python :: 3
Classifier: Programming Language :: Python :: 3.6
Classifier: Programming Language :: Python :: 3.7
Classifier: Programming Language :: Python :: 3.8
Classifier: Programming Language :: Python :: 3.9
Requires-Dist: pandas
Requires-Dist: pandas-datareader
Requires-Dist: telebot
Requires-Dist: yfinance
